jqi/__init__.py
jqi/cmd.py
jqi/completer.py
jqi/completion.py
jqi/editor.py
jqi/error.py
jqi/eval.py
jqi/function.py
jqi/lexer.py
jqi/parser.py
jqi/pattern.py
jqi-0.1.0.dist-info/licenses/LICENCE.md
jqi-0.1.0.dist-info/METADATA
jqi-0.1.0.dist-info/WHEEL
jqi-0.1.0.dist-info/entry_points.txt
jqi-0.1.0.dist-info/top_level.txt
jqi-0.1.0.dist-info/RECORD
