Metadata-Version: 2.4
Name: jqi
Version: 0.1.0
Summary: An interactive wrapper for jq
Home-page: https://github.com/jan-g/jqi
Author: jan grant 
Author-email: jqi@ioctl.org
License: Apache License 2.0
License-File: LICENCE.md
Requires-Dist: argparse_helper>=0.9.1
Requires-Dist: config-dir>=0.0.5
Requires-Dist: parsy
Requires-Dist: prompt_toolkit>=3.0.5
Requires-Dist: pyyaml
Requires-Dist: sh
Dynamic: author
Dynamic: author-email
Dynamic: description
Dynamic: description-content-type
Dynamic: home-page
Dynamic: license
Dynamic: license-file
Dynamic: requires-dist
Dynamic: summary
